libpyaoaddons.cpython-36m-i386-linux-gnu.so
pyaoaddons-0.2.8.dist-info/WHEEL
pyaoaddons-0.2.8.dist-info/top_level.txt
pyaoaddons-0.2.8.dist-info/METADATA
pyaoaddons-0.2.8.dist-info/RECORD
pyaoaddons/__init__.py
pyaoaddons/item_category_mapping.py
pyaoaddons/localization_mapping.py
pyaoaddons.libs/libkrb5support-985cac75.so.0.1
pyaoaddons.libs/libcrypto-526a6201.so.1.0.1e
pyaoaddons.libs/libcom_err-20437120.so.2.1
pyaoaddons.libs/libssl-227cedef.so.1.0.1e
pyaoaddons.libs/libkrb5-d3a1a4c9.so.3.3
pyaoaddons.libs/libgssapi_krb5-c362d938.so.2.2
pyaoaddons.libs/libselinux-10a8adc8.so.1
pyaoaddons.libs/libkeyutils-94914291.so.1.3
pyaoaddons.libs/libk5crypto-3e7ee1bc.so.3.1
