Metadata-Version: 2.1
Name: pyaoaddons
Version: 0.2.8
Summary: UNKNOWN
Home-page: https://github.com/mazurwiktor/aoaddons-python
Author: Wiktor Mazur
Author-email: wiktormazur1@gmail.com
License: UNKNOWN
Platform: UNKNOWN
